iqube/SiNo.py
iqube/__init__.py
iqube/calculation.py
iqube/default_config.py
iQube-0.0.1.dist-info/LICENSE
iQube-0.0.1.dist-info/METADATA
iQube-0.0.1.dist-info/WHEEL
iQube-0.0.1.dist-info/top_level.txt
iQube-0.0.1.dist-info/RECORD
