Metadata-Version: 2.1
Name: iQube
Version: 0.0.1
Summary: A package to analyze data from linien
Home-page: https://github.com/AaronStra/SiNo
Author: Aaron Strangfeld
Author-email: a.strangfeld@web.de
License: UNKNOWN
Platform: UNKNOWN
Classifier: Programming Language :: Python :: 3
Classifier: License :: OSI Approved :: MIT License
Classifier: Operating System :: OS Independent
Requires-Python: >=3.6
